pycdp/__init__.py
pycdp/__init__.pyi
pycdp/client.py
pycdp/client.pyi
pycdp/py.typed
pycdp_client-1.0.4.dist-info/METADATA
pycdp_client-1.0.4.dist-info/WHEEL
pycdp_client-1.0.4.dist-info/top_level.txt
pycdp_client-1.0.4.dist-info/RECORD
