Metadata-Version: 2.4
Name: pycdp-client
Version: 1.0.4
Summary: Chrome DevTools Protocol 客户端，支持独立使用或与 DrissionPage 配合
Author: letme58
License-Expression: MIT
Project-URL: Homepage, https://github.com/letme58/pycdp
Requires-Python: >=3.8
Requires-Dist: requests
Requires-Dist: websocket-client
Provides-Extra: drissionpage
Requires-Dist: DrissionPage; extra == "drissionpage"
